lentille/__init__.py
lentille/base_embedder.py
lentille/embedders/vision/Resnet50Embedder.py
lentille/utils/resnet50_preprocess.py
lentille-0.3.0.dist-info/METADATA
lentille-0.3.0.dist-info/WHEEL
lentille-0.3.0.dist-info/RECORD
