Metadata-Version: 2.1
Name: lentille
Version: 0.3.0
Summary: 
Author: Alex
Author-email: 46456279+the-alex-b@users.noreply.github.com
Requires-Python: >=3.9,<4.0
Classifier: Programming Language :: Python :: 3
Classifier: Programming Language :: Python :: 3.9
Classifier: Programming Language :: Python :: 3.10
Classifier: Programming Language :: Python :: 3.11
Requires-Dist: numpy (>=1.24.3,<2.0.0)
Requires-Dist: onnxruntime (>=1.14.1,<2.0.0)
Requires-Dist: pillow (>=9.5.0,<10.0.0)
